Metadata-Version: 2.1
Name: odoo-addon-account_check_printing_report_base
Version: 19.0.1.0.0.2
Requires-Dist: num2words
Requires-Dist: odoo==19.0.*
Summary: Account Check Printing Report Base
Home-page: https://github.com/OCA/account-payment
License: AGPL-3
Author: ForgeFlow,Serpent Consulting Services Pvt. Ltd.,Ursa Information Systems,Odoo Community Association (OCA)
Author-email: support@odoo-community.org
Classifier: Programming Language :: Python
Classifier: Framework :: Odoo
Classifier: Framework :: Odoo :: 19.0
Classifier: License :: OSI Approved :: GNU Affero General Public License v3
